momify-0.0.13.dist-info/METADATA
momify-0.0.13.dist-info/WHEEL
momify-0.0.13.dist-info/entry_points.txt
momify/loopback/record.cp38-win_amd64.pyd
momify/loopback/record.cp38-win_amd64.lib
momify/__init__.py
momify/__main__.py
momify/cli.py
momify/momify.py
momify/loopback/__init__.py
momify/utils/__init__.py
momify/utils/summarize.py
momify/utils/transcribe.py
momify-0.0.13.dist-info/RECORD
