Metadata-Version: 2.1
Name: momify
Version: 0.0.13
Summary: A tool for seamlessly summarizing your boring meetings!
Author: Athirah Hazwani
Project-URL: Source, https://github.com/xyzinabox/MoMify
Requires-Python: >=3.8
Requires-Dist: typer
Requires-Dist: transformers
Requires-Dist: accelerate
